queso/__init__.py
queso/__main__.py
queso/commands.py
queso/utils.py
queso/versions.py
queso/cli/__init__.py
queso/cli/commands.py
queso/cli/factory.py
queso/cli/options.py
queso/scaffold/__init__.py
queso/scaffold/utils.py
tests/__init__.py
tests/conftest.py
tests/test_call_command.py
tests/test_custom_commands.py
tests/test_invoke.py
tests/test_version.py
tests/utils.py
queso-0.2.1.dist-info/LICENSE
queso-0.2.1.dist-info/METADATA
queso-0.2.1.dist-info/WHEEL
queso-0.2.1.dist-info/entry_points.txt
queso-0.2.1.dist-info/top_level.txt
queso-0.2.1.dist-info/RECORD
